README.rst
setup.py
examples/concurrent_external_api/__init__.py
examples/concurrent_external_api/app.py
examples/concurrent_external_api/auth.py
examples/concurrent_external_api/filter.py
examples/concurrent_external_api/schema.py
examples/concurrent_external_api/source.py
examples/concurrent_external_api/tests/__init__.py
examples/concurrent_external_api/tests/test_app_details.py
examples/external_api/__init__.py
examples/external_api/app.py
examples/external_api/auth.py
examples/external_api/filter.py
examples/external_api/schema.py
examples/external_api/source.py
examples/external_api/tests/__init__.py
examples/external_api/tests/test_app_details.py
examples/external_api/tests/test_flatfile_source.py
examples/flatfile/__init__.py
examples/flatfile/app.py
examples/flatfile/auth.py
examples/flatfile/filter.py
examples/flatfile/source.py
examples/flatfile/tests/__init__.py
examples/flatfile/tests/test_app_details.py
examples/flatfile/tests/test_flatfile_filterlists.py
examples/flatfile/tests/test_flatfile_source.py
vizydrop/__init__.py
vizydrop/fields.py
vizydrop/tpa.py
vizydrop/utils.py
vizydrop/rest/__init__.py
vizydrop/rest/account.py
vizydrop/rest/base.py
vizydrop/rest/filter.py
vizydrop/rest/handlers.py
vizydrop/rest/logo.py
vizydrop/sdk/__init__.py
vizydrop/sdk/account.py
vizydrop/sdk/application.py
vizydrop/sdk/source.py
vizydrop/tests/__init__.py
vizydrop/tests/test_fieldobject.py
vizydrop/tests/test_fields.py
vizydrop/tests/test_schema_generation.py
vizydrop/tests/test_utilities.py
vizydrop_sdk.egg-info/PKG-INFO
vizydrop_sdk.egg-info/SOURCES.txt
vizydrop_sdk.egg-info/dependency_links.txt
vizydrop_sdk.egg-info/requires.txt
vizydrop_sdk.egg-info/top_level.txt