Metadata-Version: 1.1
Name: vizydrop-sdk
Version: 0.6.0
Summary: Vizydrop 3rd Party Application Python SDK - Get visual
Home-page: https://github.com/vizydrop/vizydrop-python-sdk
Author: Jonathan Enzinna
Author-email: jonathan@vizydrop.com
License: MIT
Keywords: sdk visualization vizydrop
Platform: UNKNOWN
Classifier: Development Status :: 3 - Alpha
Classifier: Topic :: Software Development :: Libraries :: Python Modules
Classifier: Topic :: Scientific/Engineering :: Visualization
Classifier: License :: OSI Approved :: MIT License
Classifier: Intended Audience :: Developers
Classifier: Operating System :: OS Independent
Classifier: Programming Language :: Python :: 3 :: Only
